ooui/__init__.py
ooui/graph/__init__.py
ooui/graph/axis.py
ooui/graph/base.py
ooui/graph/chart.py
ooui/graph/fields.py
ooui/graph/indicator.py
ooui/graph/processor.py
ooui/graph/timerange.py
ooui/helpers/__init__.py
ooui/helpers/aggregated.py
ooui/helpers/conditions.py
ooui/helpers/dates.py
ooui/helpers/domain.py
ooui/helpers/features.py
ooui/tree/__init__.py
ooui/tree/base.py
ooui-0.19.0.dist-info/licenses/LICENSE
ooui-0.19.0.dist-info/METADATA
ooui-0.19.0.dist-info/WHEEL
ooui-0.19.0.dist-info/top_level.txt
ooui-0.19.0.dist-info/RECORD
