Metadata-Version: 2.4
Name: ooui
Version: 0.19.0
Summary: Open Object User Interface
Home-page: https://github.com/gisce/python-ooui
Author: GISCE
Author-email: devel@gisce.net
License: MIT
Provides: ooui
License-File: LICENSE
Requires-Dist: lxml
Requires-Dist: python-dateutil
Requires-Dist: six
Requires-Dist: simpleeval<0.9.12
Dynamic: author
Dynamic: author-email
Dynamic: description
Dynamic: home-page
Dynamic: license
Dynamic: license-file
Dynamic: provides
Dynamic: requires-dist
Dynamic: summary
